tsquared/__init__.py
tsquared/hotelling_t2.py
tsquared/myt_decomposition.py
tsquared/utils.py
tsquared-1.1.0.dist-info/LICENSE
tsquared-1.1.0.dist-info/METADATA
tsquared-1.1.0.dist-info/WHEEL
tsquared-1.1.0.dist-info/top_level.txt
tsquared-1.1.0.dist-info/RECORD
