Metadata-Version: 2.1
Name: tsquared
Version: 1.1.0
Summary: Hotelling's T-squared (T2) for process monitoring and MYT decomposition
Home-page: https://github.com/cetic/tsquared
Author: Nico Salamone, Paul Vanabelle
Author-email: nico.salamone2411@gmail.com, paul.vanabelle@cetic.be
License: MIT
Classifier: Development Status :: 5 - Production/Stable
Classifier: Intended Audience :: Developers
Classifier: Intended Audience :: Education
Classifier: Intended Audience :: Financial and Insurance Industry
Classifier: Intended Audience :: Healthcare Industry
Classifier: Intended Audience :: Information Technology
Classifier: Intended Audience :: Manufacturing
Classifier: Intended Audience :: Science/Research
Classifier: License :: OSI Approved :: MIT License
Classifier: Programming Language :: Python :: 3 :: Only
Classifier: Topic :: Scientific/Engineering
Classifier: Topic :: Software Development :: Libraries
Classifier: Topic :: Software Development :: Libraries :: Python Modules
Requires-Python: >=3.6.0
License-File: LICENSE
Requires-Dist: numpy
Requires-Dist: pingouin
Requires-Dist: scikit-learn
Requires-Dist: scipy
